Trinitum/AsyncManager.py
Trinitum/Constants.py
Trinitum/DatabaseManager.py
Trinitum/Diagnostics.py
Trinitum/Order.py
Trinitum/Pipeline.py
Trinitum/Position.py
Trinitum/RSU.py
Trinitum/Strategy.py
Trinitum/TradingInstance.py
Trinitum/Trinitum.py
Trinitum/Utilities.py
Trinitum/__init__.py
Trinitum-0.5.dist-info/DESCRIPTION.rst
Trinitum-0.5.dist-info/METADATA
Trinitum-0.5.dist-info/RECORD
Trinitum-0.5.dist-info/WHEEL
Trinitum-0.5.dist-info/metadata.json
Trinitum-0.5.dist-info/top_level.txt
