Metadata-Version: 2.0
Name: Trinitum
Version: 0.5
Summary: Dead simple algorithmic cryptocurrency trading system.
Home-page: https://github.com/themichaelusa/Trinitum
Author: Michael Usachenko
Author-email: meu2@illinois.edu
License: UNKNOWN
Download-URL: https://github.com/themichaelusa/Trinitum/archive/0.05.tar.gz
Keywords: Trinitum,algotrading,cryptocurrency,bots
Platform: UNKNOWN
Requires-Dist: AsyncPQ
Requires-Dist: ciso8601
Requires-Dist: gdax
Requires-Dist: numpy
Requires-Dist: pandas
Requires-Dist: python-dateutil
Requires-Dist: realtime-talib
Requires-Dist: requests
Requires-Dist: rethinkdb
